logfmt/__init__.py
logfmt/formatter.py
logfmt/parser.py
logfmt-0.4.dist-info/METADATA
logfmt-0.4.dist-info/RECORD
logfmt-0.4.dist-info/WHEEL
logfmt-0.4.dist-info/top_level.txt
